zbricklib_sqla/__init__.py
zbricklib_sqla/py.typed
zbricklib_sqla-0.1.1.dist-info/METADATA
zbricklib_sqla-0.1.1.dist-info/WHEEL
zbricklib_sqla-0.1.1.dist-info/RECORD
