Metadata-Version: 2.1
Name: zbricklib-sqla
Version: 0.1.1
Summary: Flask-SQLAlchemy wrapper for zbricklib
Author: zdeyn
Author-email: zdeyn@zdeyn.com
Requires-Python: >=3.10,<4.0
Classifier: Programming Language :: Python :: 3
Classifier: Programming Language :: Python :: 3.10
Classifier: Programming Language :: Python :: 3.11
Classifier: Programming Language :: Python :: 3.12
Requires-Dist: flask-sqlalchemy (>=3.1.1,<4.0.0)
Requires-Dist: zbricklib (>=0.1.0,<0.2.0)
